openssm/Makefile
openssm/README.md
openssm/VERSION
openssm/__init__.py
openssm/contrib/README.md
openssm/contrib/__init__.py
openssm/contrib/streamlit_chatssm.py
openssm/core/__init__.py
openssm/core/adapter/__init__.py
openssm/core/adapter/abstract_adapter.py
openssm/core/adapter/base_adapter.py
openssm/core/backend/__init__.py
openssm/core/backend/abstract_backend.py
openssm/core/backend/base_backend.py
openssm/core/backend/rag_backend.py
openssm/core/backend/text_backend.py
openssm/core/inferencer/__init__.py
openssm/core/inferencer/abstract_inferencer.py
openssm/core/inferencer/base_inferencer.py
openssm/core/prompts.py
openssm/core/slm/__init__.py
openssm/core/slm/abstract_slm.py
openssm/core/slm/base_slm.py
openssm/core/slm/memory/__init__.py
openssm/core/slm/memory/conversation_db.py
openssm/core/slm/memory/sqlite_conversation_db.py
openssm/core/ssm/__init__.py
openssm/core/ssm/abstract_ssm.py
openssm/core/ssm/abstract_ssm_builder.py
openssm/core/ssm/base_ssm.py
openssm/core/ssm/base_ssm_builder.py
openssm/core/ssm/rag_ssm.py
openssm/industrial/interpretability/README.md
openssm/industrial/monitoring/README.md
openssm/industrial/security/README.md
openssm/industrial/security/audit/README.md
openssm/industrial/security/best_practices/README.md
openssm/integrations/README.md
openssm/integrations/__init__.py
openssm/integrations/api_context.py
openssm/integrations/azure/ssm.py
openssm/integrations/huggingface/__init__.py
openssm/integrations/huggingface/slm.py
openssm/integrations/huggingface/ssm.py
openssm/integrations/lepton_ai/__init__.py
openssm/integrations/lepton_ai/ssm.py
openssm/integrations/llama_index/README.md
openssm/integrations/llama_index/__init__.py
openssm/integrations/llama_index/backend.py
openssm/integrations/llama_index/ssm.py
openssm/integrations/openai/__init__.py
openssm/integrations/openai/ssm.py
openssm/integrations/testing_tools/README.md
openssm/utils/__init__.py
openssm/utils/config.py
openssm/utils/fs.py
openssm/utils/logs.py
openssm_dev-0.1.6.29.dist-info/LICENSE.md
openssm_dev-0.1.6.29.dist-info/METADATA
openssm_dev-0.1.6.29.dist-info/WHEEL
openssm_dev-0.1.6.29.dist-info/RECORD
