Metadata-Version: 2.1
Name: openssm-dev
Version: 0.1.6.29
Summary: OpenSSM - 'Small Specialist Models' for Industrial AI
Author: Aitomatic Engineering
Author-email: engineering@aitomatic.com
Requires-Python: >=3.8.1,<4.0
Classifier: Programming Language :: Python :: 3
Classifier: Programming Language :: Python :: 3.9
Classifier: Programming Language :: Python :: 3.10
Classifier: Programming Language :: Python :: 3.11
Provides-Extra: cv
Requires-Dist: adlfs (>=2023.8.0)
Requires-Dist: docx2txt (>=0.8)
Requires-Dist: fsspec (>=2023.6.0)
Requires-Dist: gcsfs (>=2023.6.0)
Requires-Dist: gdrivefs (>=0.14.13)
Requires-Dist: google-api-python-client (>=2.0)
Requires-Dist: llama-hub (>=0.0.25)
Requires-Dist: llama-index (>=0.8.8)
Requires-Dist: nltk (>=3.8.1)
Requires-Dist: openai (>=0.27)
Requires-Dist: pillow (>=0.9.5) ; extra == "cv"
Requires-Dist: pycryptodome (>=3.18.0)
Requires-Dist: pydantic (>=1.10)
Requires-Dist: pydocstyle (>=6.3.0)
Requires-Dist: pypdf (>=3.15.2)
Requires-Dist: pytest (>=7.0.0)
Requires-Dist: python-dotenv (>=0.19.0)
Requires-Dist: python-pptx (>=0.6.22) ; extra == "cv"
Requires-Dist: s3fs (>=2023.6.0)
Requires-Dist: torch (>=2.0.1) ; extra == "cv"
Requires-Dist: transformers (>=4.33.1) ; extra == "cv"
